LscNumbers/Numbers.py
LscNumbers/__init__.py
lscnumbers-0.0.9.dist-info/licenses/LICENSE
lscnumbers-0.0.9.dist-info/METADATA
lscnumbers-0.0.9.dist-info/WHEEL
lscnumbers-0.0.9.dist-info/top_level.txt
lscnumbers-0.0.9.dist-info/RECORD
