Metadata-Version: 2.4
Name: LscNumbers
Version: 0.0.9
Summary: 用于精确计算的数字类
Author-email: Linsc <1344343923@qq.com>
Classifier: Programming Language :: Python :: 3
Classifier: License :: OSI Approved :: MIT License
Classifier: Operating System :: OS Independent
Requires-Python: >=3.7
License-File: LICENSE
Requires-Dist: LscCalculator
Dynamic: license-file
